LICENSE
MANIFEST.in
README.md
setup.py
uwsgiit/__init__.py
uwsgiit/api.py
uwsgiit/models.py
uwsgiit/tests.py
uwsgiit_py.egg-info/PKG-INFO
uwsgiit_py.egg-info/SOURCES.txt
uwsgiit_py.egg-info/dependency_links.txt
uwsgiit_py.egg-info/not-zip-safe
uwsgiit_py.egg-info/requires.txt
uwsgiit_py.egg-info/top_level.txt