Metadata-Version: 1.1
Name: uwsgiit-py
Version: 0.8.0
Summary: Library for uwsgi.it api
Home-page: https://github.com/xrmx/uwsgiit-py
Author: Riccardo Magliocchetti
Author-email: riccardo@unbit.it
License: BSD License
Platform: OS Independent
Classifier: Environment :: Console
Classifier: Intended Audience :: Developers
Classifier: Intended Audience :: System Administrators
Classifier: License :: OSI Approved :: BSD License
Classifier: Operating System :: OS Independent
Classifier: Programming Language :: Python
Classifier: Topic :: Software Development :: Libraries :: Python Modules
